{
  "pages": [
    {
      "path": "pages/douyin/index",
      "style": {
        "navigationBarTitleText": "",
        "enablePullDownRefresh": false
      }
    },
    {
      "path": "pages/douyin/douyin",
      "style": {
        "navigationBarTitleText": "",
        "enablePullDownRefresh": false,
        "navigationBarBackgroundColor": "#fff"
      }
    },
    {
      "path": "pages/wallpaper/wallpaper",
      "style": {
        "navigationBarTitleText": "壁纸港湾",
        "enablePullDownRefresh": false,
        "navigationBarBackgroundColor": "#fff",
        "navigationStyle": "custom"
      }
    },
    {
      "path": "pages/wallpaper/details",
      "style": {
        "navigationBarTitleText": "壁纸详情",
        "enablePullDownRefresh": false,
        "navigationStyle": "custom"
      }
    },
    {
      "path": "pages/my/my",
      "style": {
        "navigationBarTitleText": "我的",
        "enablePullDownRefresh": false,
        "navigationStyle": "custom"
      }
    },
    {
      "path": "pages/my/info",
      "style": {
        "navigationBarTitleText": "编辑资料",
        "enablePullDownRefresh": false,
        "navigationBarBackgroundColor": "#fff"
      }
    },
    {
      "path": "pages/my/name",
      "style": {
        "navigationBarTitleText": "修改昵称",
        "enablePullDownRefresh": false
      }
    },
    {
      "path": "pages/login/login",
      "style": {
        "navigationBarTitleText": "登录",
        "enablePullDownRefresh": false
      }
    },
    {
      "path": "pages/login/qrcode",
      "style": {
        "navigationBarTitleText": "扫码登录",
        "enablePullDownRefresh": false,
        "navigationBarBackgroundColor": "#fff",
        "navigationStyle": "custom"
      }
    },
    {
      "path": "pages/forms/forms",
      "style": {
        "navigationBarTitleText": "我的九阴账号",
        "enablePullDownRefresh": false
      }
    },
    {
      "path": "pages/news/9yinDetail",
      "style": {
        "navigationBarTitleText": "新闻详情",
        "enablePullDownRefresh": false
      }
    },
    {
      "path": "pages/forms/list",
      "style": {
        "navigationBarTitleText": "我的九阴",
        "enablePullDownRefresh": false
      }
    },
    {
      "path": "pages/admin/gameAccounts",
      "style": {
        "navigationBarTitleText": "游戏账号",
        "enablePullDownRefresh": false
      }
    },
    {
      "path": "pages/address/list",
      "style": {
        "navigationBarTitleText": "我的地址",
        "enablePullDownRefresh": false
      }
    },
    {
      "path": "pages/address/add",
      "style": {
        "navigationBarTitleText": "我的地址",
        "enablePullDownRefresh": false
      }
    }
  ],
  "globalStyle": {
    "navigationBarTextStyle": "black",
    "navigationBarTitleText": "画卷",
    "navigationBarBackgroundColor": "#F8F8F8",
    "backgroundColor": "#F8F8F8"
  },
  "tabBar": {
    "color": "#8a8a8a",
    "selectedColor": "#6565fd",
    "borderStyle": "white",
    "backgroundColor": "#fff",
    "list": [
      {
        "pagePath": "pages/douyin/index",
        "text": "首页",
        "iconPath": "static/images/tabbar/index.png",
        "selectedIconPath": "static/images/tabbar/index_active.png"
      },
      {
        "pagePath": "pages/my/my",
        "text": "我的",
        "iconPath": "static/images/tabbar/my.png",
        "selectedIconPath": "static/images/tabbar/my_active.png"
      }
    ]
  }
}
